[
    {
        "id": 703,
        "temperature": 21.45,
        "humidity": 75.99,
        "co2": 532.0,
        "light": 87.08,
        "wind_speed": 0.0,
        "moisture1": 24.87,
        "moisture2": 45.09,
        "moisture3": 99.18,
        "moisture4": 100.0,
        "nitrogen": 1.29,
        "phosphorus": 7.56,
        "potassium": 1.14,
        "ec": 1036.0,
        "ph": 7.6,
        "timestamp": "2025-04-15T12:08:08+02:00"
    },
    {
        "id": 704,
        "temperature": 21.49,
        "humidity": 75.8,
        "co2": 522.0,
        "light": 81.25,
        "wind_speed": 0.0,
        "moisture1": 24.4,
        "moisture2": 43.09,
        "moisture3": 95.83,
        "moisture4": 100.0,
        "nitrogen": 1.32,
        "phosphorus": 7.53,
        "potassium": 1.15,
        "ec": 1033.0,
        "ph": 7.6,
        "timestamp": "2025-04-15T12:18:08+02:00"
    },
    {
        "id": 705,
        "temperature": 21.56,
        "humidity": 75.43,
        "co2": 494.0,
        "light": 82.08,
        "wind_speed": 0.0,
        "moisture1": 24.1,
        "moisture2": 44.86,
        "moisture3": 98.41,
        "moisture4": 100.0,
        "nitrogen": 1.33,
        "phosphorus": 7.52,
        "potassium": 1.15,
        "ec": 1030.0,
        "ph": 7.7,
        "timestamp": "2025-04-15T12:28:08+02:00"
    },
    {
        "id": 706,
        "temperature": 21.59,
        "humidity": 75.18,
        "co2": 483.0,
        "light": 91.25,
        "wind_speed": 0.0,
        "moisture1": 24.99,
        "moisture2": 45.39,
        "moisture3": 99.18,
        "moisture4": 100.0,
        "nitrogen": 1.29,
        "phosphorus": 7.58,
        "potassium": 1.13,
        "ec": 1046.0,
        "ph": 7.7,
        "timestamp": "2025-04-15T12:38:08+02:00"
    },
    {
        "id": 707,
        "temperature": 21.65,
        "humidity": 75.0,
        "co2": 468.0,
        "light": 76.67,
        "wind_speed": 0.0,
        "moisture1": 24.69,
        "moisture2": 45.15,
        "moisture3": 95.94,
        "moisture4": 100.0,
        "nitrogen": 1.29,
        "phosphorus": 7.6,
        "potassium": 1.11,
        "ec": 1042.0,
        "ph": 7.7,
        "timestamp": "2025-04-15T12:48:08+02:00"
    }
]