[
    {
        "id": 178,
        "temperature": 17.12,
        "humidity": 84.92,
        "co2": 686.0,
        "light": 0.0,
        "wind_speed": 0.0,
        "moisture1": 97.24,
        "moisture2": 0.0,
        "moisture3": 96.88,
        "moisture4": 0.0,
        "nitrogen": 0.71,
        "phosphorus": 4.93,
        "potassium": 4.36,
        "ec": 917.0,
        "ph": 7.3,
        "timestamp": "2025-02-22T06:09:48+01:00"
    },
    {
        "id": 179,
        "temperature": 17.11,
        "humidity": 84.91,
        "co2": 690.0,
        "light": 0.0,
        "wind_speed": 0.0,
        "moisture1": 98.77,
        "moisture2": 0.0,
        "moisture3": 95.47,
        "moisture4": 0.0,
        "nitrogen": 0.76,
        "phosphorus": 4.97,
        "potassium": 4.28,
        "ec": 915.0,
        "ph": 7.8,
        "timestamp": "2025-02-22T06:19:48+01:00"
    },
    {
        "id": 180,
        "temperature": 17.14,
        "humidity": 84.86,
        "co2": 694.0,
        "light": 0.0,
        "wind_speed": 0.0,
        "moisture1": 97.88,
        "moisture2": 0.0,
        "moisture3": 97.0,
        "moisture4": 0.0,
        "nitrogen": 0.71,
        "phosphorus": 4.93,
        "potassium": 4.36,
        "ec": 919.0,
        "ph": 7.8,
        "timestamp": "2025-02-22T06:29:48+01:00"
    },
    {
        "id": 181,
        "temperature": 17.09,
        "humidity": 84.96,
        "co2": 695.0,
        "light": 0.0,
        "wind_speed": 0.0,
        "moisture1": 97.59,
        "moisture2": 0.0,
        "moisture3": 98.94,
        "moisture4": 0.0,
        "nitrogen": 0.72,
        "phosphorus": 4.96,
        "potassium": 4.32,
        "ec": 914.0,
        "ph": 7.4,
        "timestamp": "2025-02-22T06:39:48+01:00"
    },
    {
        "id": 182,
        "temperature": 17.09,
        "humidity": 85.03,
        "co2": 700.0,
        "light": 0.0,
        "wind_speed": 0.0,
        "moisture1": 99.47,
        "moisture2": 0.0,
        "moisture3": 99.12,
        "moisture4": 0.0,
        "nitrogen": 0.5,
        "phosphorus": 5.04,
        "potassium": 4.46,
        "ec": 918.0,
        "ph": 8.0,
        "timestamp": "2025-02-22T06:49:48+01:00"
    },
    {
        "id": 183,
        "temperature": 17.07,
        "humidity": 85.02,
        "co2": 701.0,
        "light": 0.0,
        "wind_speed": 0.0,
        "moisture1": 97.59,
        "moisture2": 0.0,
        "moisture3": 97.12,
        "moisture4": 0.0,
        "nitrogen": 0.72,
        "phosphorus": 5.04,
        "potassium": 4.24,
        "ec": 919.0,
        "ph": 7.7,
        "timestamp": "2025-02-22T06:59:48+01:00"
    },
    {
        "id": 178,
        "temperature": 17.12,
        "humidity": 84.92,
        "co2": 686.0,
        "light": 0.0,
        "wind_speed": 0.0,
        "moisture1": 97.24,
        "moisture2": 0.0,
        "moisture3": 96.88,
        "moisture4": 0.0,
        "nitrogen": 0.71,
        "phosphorus": 4.93,
        "potassium": 4.36,
        "ec": 917.0,
        "ph": 7.3,
        "timestamp": "2025-02-22T06:09:48+01:00"
    },
    {
        "id": 179,
        "temperature": 17.11,
        "humidity": 84.91,
        "co2": 690.0,
        "light": 0.0,
        "wind_speed": 0.0,
        "moisture1": 98.77,
        "moisture2": 0.0,
        "moisture3": 95.47,
        "moisture4": 0.0,
        "nitrogen": 0.76,
        "phosphorus": 4.97,
        "potassium": 4.28,
        "ec": 915.0,
        "ph": 7.8,
        "timestamp": "2025-02-22T06:19:48+01:00"
    },
    {
        "id": 180,
        "temperature": 17.14,
        "humidity": 84.86,
        "co2": 694.0,
        "light": 0.0,
        "wind_speed": 0.0,
        "moisture1": 97.88,
        "moisture2": 0.0,
        "moisture3": 97.0,
        "moisture4": 0.0,
        "nitrogen": 0.71,
        "phosphorus": 4.93,
        "potassium": 4.36,
        "ec": 919.0,
        "ph": 7.8,
        "timestamp": "2025-02-22T06:29:48+01:00"
    },
    {
        "id": 181,
        "temperature": 17.09,
        "humidity": 84.96,
        "co2": 695.0,
        "light": 0.0,
        "wind_speed": 0.0,
        "moisture1": 97.59,
        "moisture2": 0.0,
        "moisture3": 98.94,
        "moisture4": 0.0,
        "nitrogen": 0.72,
        "phosphorus": 4.96,
        "potassium": 4.32,
        "ec": 914.0,
        "ph": 7.4,
        "timestamp": "2025-02-22T06:39:48+01:00"
    },
    {
        "id": 182,
        "temperature": 17.09,
        "humidity": 85.03,
        "co2": 700.0,
        "light": 0.0,
        "wind_speed": 0.0,
        "moisture1": 99.47,
        "moisture2": 0.0,
        "moisture3": 99.12,
        "moisture4": 0.0,
        "nitrogen": 0.5,
        "phosphorus": 5.04,
        "potassium": 4.46,
        "ec": 918.0,
        "ph": 8.0,
        "timestamp": "2025-02-22T06:49:48+01:00"
    },
    {
        "id": 183,
        "temperature": 17.07,
        "humidity": 85.02,
        "co2": 701.0,
        "light": 0.0,
        "wind_speed": 0.0,
        "moisture1": 97.59,
        "moisture2": 0.0,
        "moisture3": 97.12,
        "moisture4": 0.0,
        "nitrogen": 0.72,
        "phosphorus": 5.04,
        "potassium": 4.24,
        "ec": 919.0,
        "ph": 7.7,
        "timestamp": "2025-02-22T06:59:48+01:00"
    },
    {
        "id": 178,
        "temperature": 17.12,
        "humidity": 84.92,
        "co2": 686.0,
        "light": 0.0,
        "wind_speed": 0.0,
        "moisture1": 97.24,
        "moisture2": 0.0,
        "moisture3": 96.88,
        "moisture4": 0.0,
        "nitrogen": 0.71,
        "phosphorus": 4.93,
        "potassium": 4.36,
        "ec": 917.0,
        "ph": 7.3,
        "timestamp": "2025-02-22T06:09:48+01:00"
    },
    {
        "id": 179,
        "temperature": 17.11,
        "humidity": 84.91,
        "co2": 690.0,
        "light": 0.0,
        "wind_speed": 0.0,
        "moisture1": 98.77,
        "moisture2": 0.0,
        "moisture3": 95.47,
        "moisture4": 0.0,
        "nitrogen": 0.76,
        "phosphorus": 4.97,
        "potassium": 4.28,
        "ec": 915.0,
        "ph": 7.8,
        "timestamp": "2025-02-22T06:19:48+01:00"
    },
    {
        "id": 180,
        "temperature": 17.14,
        "humidity": 84.86,
        "co2": 694.0,
        "light": 0.0,
        "wind_speed": 0.0,
        "moisture1": 97.88,
        "moisture2": 0.0,
        "moisture3": 97.0,
        "moisture4": 0.0,
        "nitrogen": 0.71,
        "phosphorus": 4.93,
        "potassium": 4.36,
        "ec": 919.0,
        "ph": 7.8,
        "timestamp": "2025-02-22T06:29:48+01:00"
    },
    {
        "id": 181,
        "temperature": 17.09,
        "humidity": 84.96,
        "co2": 695.0,
        "light": 0.0,
        "wind_speed": 0.0,
        "moisture1": 97.59,
        "moisture2": 0.0,
        "moisture3": 98.94,
        "moisture4": 0.0,
        "nitrogen": 0.72,
        "phosphorus": 4.96,
        "potassium": 4.32,
        "ec": 914.0,
        "ph": 7.4,
        "timestamp": "2025-02-22T06:39:48+01:00"
    },
    {
        "id": 182,
        "temperature": 17.09,
        "humidity": 85.03,
        "co2": 700.0,
        "light": 0.0,
        "wind_speed": 0.0,
        "moisture1": 99.47,
        "moisture2": 0.0,
        "moisture3": 99.12,
        "moisture4": 0.0,
        "nitrogen": 0.5,
        "phosphorus": 5.04,
        "potassium": 4.46,
        "ec": 918.0,
        "ph": 8.0,
        "timestamp": "2025-02-22T06:49:48+01:00"
    },
    {
        "id": 183,
        "temperature": 17.07,
        "humidity": 85.02,
        "co2": 701.0,
        "light": 0.0,
        "wind_speed": 0.0,
        "moisture1": 97.59,
        "moisture2": 0.0,
        "moisture3": 97.12,
        "moisture4": 0.0,
        "nitrogen": 0.72,
        "phosphorus": 5.04,
        "potassium": 4.24,
        "ec": 919.0,
        "ph": 7.7,
        "timestamp": "2025-02-22T06:59:48+01:00"
    },
    {
        "id": 178,
        "temperature": 17.12,
        "humidity": 84.92,
        "co2": 686.0,
        "light": 0.0,
        "wind_speed": 0.0,
        "moisture1": 97.24,
        "moisture2": 0.0,
        "moisture3": 96.88,
        "moisture4": 0.0,
        "nitrogen": 0.71,
        "phosphorus": 4.93,
        "potassium": 4.36,
        "ec": 917.0,
        "ph": 7.3,
        "timestamp": "2025-02-22T06:09:48+01:00"
    },
    {
        "id": 179,
        "temperature": 17.11,
        "humidity": 84.91,
        "co2": 690.0,
        "light": 0.0,
        "wind_speed": 0.0,
        "moisture1": 98.77,
        "moisture2": 0.0,
        "moisture3": 95.47,
        "moisture4": 0.0,
        "nitrogen": 0.76,
        "phosphorus": 4.97,
        "potassium": 4.28,
        "ec": 915.0,
        "ph": 7.8,
        "timestamp": "2025-02-22T06:19:48+01:00"
    },
    {
        "id": 180,
        "temperature": 17.14,
        "humidity": 84.86,
        "co2": 694.0,
        "light": 0.0,
        "wind_speed": 0.0,
        "moisture1": 97.88,
        "moisture2": 0.0,
        "moisture3": 97.0,
        "moisture4": 0.0,
        "nitrogen": 0.71,
        "phosphorus": 4.93,
        "potassium": 4.36,
        "ec": 919.0,
        "ph": 7.8,
        "timestamp": "2025-02-22T06:29:48+01:00"
    },
    {
        "id": 181,
        "temperature": 17.09,
        "humidity": 84.96,
        "co2": 695.0,
        "light": 0.0,
        "wind_speed": 0.0,
        "moisture1": 97.59,
        "moisture2": 0.0,
        "moisture3": 98.94,
        "moisture4": 0.0,
        "nitrogen": 0.72,
        "phosphorus": 4.96,
        "potassium": 4.32,
        "ec": 914.0,
        "ph": 7.4,
        "timestamp": "2025-02-22T06:39:48+01:00"
    },
    {
        "id": 182,
        "temperature": 17.09,
        "humidity": 85.03,
        "co2": 700.0,
        "light": 0.0,
        "wind_speed": 0.0,
        "moisture1": 99.47,
        "moisture2": 0.0,
        "moisture3": 99.12,
        "moisture4": 0.0,
        "nitrogen": 0.5,
        "phosphorus": 5.04,
        "potassium": 4.46,
        "ec": 918.0,
        "ph": 8.0,
        "timestamp": "2025-02-22T06:49:48+01:00"
    },
    {
        "id": 183,
        "temperature": 17.07,
        "humidity": 85.02,
        "co2": 701.0,
        "light": 0.0,
        "wind_speed": 0.0,
        "moisture1": 97.59,
        "moisture2": 0.0,
        "moisture3": 97.12,
        "moisture4": 0.0,
        "nitrogen": 0.72,
        "phosphorus": 5.04,
        "potassium": 4.24,
        "ec": 919.0,
        "ph": 7.7,
        "timestamp": "2025-02-22T06:59:48+01:00"
    },
    {
        "id": 178,
        "temperature": 17.12,
        "humidity": 84.92,
        "co2": 686.0,
        "light": 0.0,
        "wind_speed": 0.0,
        "moisture1": 97.24,
        "moisture2": 0.0,
        "moisture3": 96.88,
        "moisture4": 0.0,
        "nitrogen": 0.71,
        "phosphorus": 4.93,
        "potassium": 4.36,
        "ec": 917.0,
        "ph": 7.3,
        "timestamp": "2025-02-22T06:09:48+01:00"
    },
    {
        "id": 179,
        "temperature": 17.11,
        "humidity": 84.91,
        "co2": 690.0,
        "light": 0.0,
        "wind_speed": 0.0,
        "moisture1": 98.77,
        "moisture2": 0.0,
        "moisture3": 95.47,
        "moisture4": 0.0,
        "nitrogen": 0.76,
        "phosphorus": 4.97,
        "potassium": 4.28,
        "ec": 915.0,
        "ph": 7.8,
        "timestamp": "2025-02-22T06:19:48+01:00"
    },
    {
        "id": 180,
        "temperature": 17.14,
        "humidity": 84.86,
        "co2": 694.0,
        "light": 0.0,
        "wind_speed": 0.0,
        "moisture1": 97.88,
        "moisture2": 0.0,
        "moisture3": 97.0,
        "moisture4": 0.0,
        "nitrogen": 0.71,
        "phosphorus": 4.93,
        "potassium": 4.36,
        "ec": 919.0,
        "ph": 7.8,
        "timestamp": "2025-02-22T06:29:48+01:00"
    },
    {
        "id": 181,
        "temperature": 17.09,
        "humidity": 84.96,
        "co2": 695.0,
        "light": 0.0,
        "wind_speed": 0.0,
        "moisture1": 97.59,
        "moisture2": 0.0,
        "moisture3": 98.94,
        "moisture4": 0.0,
        "nitrogen": 0.72,
        "phosphorus": 4.96,
        "potassium": 4.32,
        "ec": 914.0,
        "ph": 7.4,
        "timestamp": "2025-02-22T06:39:48+01:00"
    },
    {
        "id": 182,
        "temperature": 17.09,
        "humidity": 85.03,
        "co2": 700.0,
        "light": 0.0,
        "wind_speed": 0.0,
        "moisture1": 99.47,
        "moisture2": 0.0,
        "moisture3": 99.12,
        "moisture4": 0.0,
        "nitrogen": 0.5,
        "phosphorus": 5.04,
        "potassium": 4.46,
        "ec": 918.0,
        "ph": 8.0,
        "timestamp": "2025-02-22T06:49:48+01:00"
    },
    {
        "id": 183,
        "temperature": 17.07,
        "humidity": 85.02,
        "co2": 701.0,
        "light": 0.0,
        "wind_speed": 0.0,
        "moisture1": 97.59,
        "moisture2": 0.0,
        "moisture3": 97.12,
        "moisture4": 0.0,
        "nitrogen": 0.72,
        "phosphorus": 5.04,
        "potassium": 4.24,
        "ec": 919.0,
        "ph": 7.7,
        "timestamp": "2025-02-22T06:59:48+01:00"
    },
    {
        "id": 178,
        "temperature": 17.12,
        "humidity": 84.92,
        "co2": 686.0,
        "light": 0.0,
        "wind_speed": 0.0,
        "moisture1": 97.24,
        "moisture2": 0.0,
        "moisture3": 96.88,
        "moisture4": 0.0,
        "nitrogen": 0.71,
        "phosphorus": 4.93,
        "potassium": 4.36,
        "ec": 917.0,
        "ph": 7.3,
        "timestamp": "2025-02-22T06:09:48+01:00"
    },
    {
        "id": 179,
        "temperature": 17.11,
        "humidity": 84.91,
        "co2": 690.0,
        "light": 0.0,
        "wind_speed": 0.0,
        "moisture1": 98.77,
        "moisture2": 0.0,
        "moisture3": 95.47,
        "moisture4": 0.0,
        "nitrogen": 0.76,
        "phosphorus": 4.97,
        "potassium": 4.28,
        "ec": 915.0,
        "ph": 7.8,
        "timestamp": "2025-02-22T06:19:48+01:00"
    },
    {
        "id": 180,
        "temperature": 17.14,
        "humidity": 84.86,
        "co2": 694.0,
        "light": 0.0,
        "wind_speed": 0.0,
        "moisture1": 97.88,
        "moisture2": 0.0,
        "moisture3": 97.0,
        "moisture4": 0.0,
        "nitrogen": 0.71,
        "phosphorus": 4.93,
        "potassium": 4.36,
        "ec": 919.0,
        "ph": 7.8,
        "timestamp": "2025-02-22T06:29:48+01:00"
    },
    {
        "id": 181,
        "temperature": 17.09,
        "humidity": 84.96,
        "co2": 695.0,
        "light": 0.0,
        "wind_speed": 0.0,
        "moisture1": 97.59,
        "moisture2": 0.0,
        "moisture3": 98.94,
        "moisture4": 0.0,
        "nitrogen": 0.72,
        "phosphorus": 4.96,
        "potassium": 4.32,
        "ec": 914.0,
        "ph": 7.4,
        "timestamp": "2025-02-22T06:39:48+01:00"
    },
    {
        "id": 182,
        "temperature": 17.09,
        "humidity": 85.03,
        "co2": 700.0,
        "light": 0.0,
        "wind_speed": 0.0,
        "moisture1": 99.47,
        "moisture2": 0.0,
        "moisture3": 99.12,
        "moisture4": 0.0,
        "nitrogen": 0.5,
        "phosphorus": 5.04,
        "potassium": 4.46,
        "ec": 918.0,
        "ph": 8.0,
        "timestamp": "2025-02-22T06:49:48+01:00"
    },
    {
        "id": 183,
        "temperature": 17.07,
        "humidity": 85.02,
        "co2": 701.0,
        "light": 0.0,
        "wind_speed": 0.0,
        "moisture1": 97.59,
        "moisture2": 0.0,
        "moisture3": 97.12,
        "moisture4": 0.0,
        "nitrogen": 0.72,
        "phosphorus": 5.04,
        "potassium": 4.24,
        "ec": 919.0,
        "ph": 7.7,
        "timestamp": "2025-02-22T06:59:48+01:00"
    },
    {
        "id": 178,
        "temperature": 17.12,
        "humidity": 84.92,
        "co2": 686.0,
        "light": 0.0,
        "wind_speed": 0.0,
        "moisture1": 97.24,
        "moisture2": 0.0,
        "moisture3": 96.88,
        "moisture4": 0.0,
        "nitrogen": 0.71,
        "phosphorus": 4.93,
        "potassium": 4.36,
        "ec": 917.0,
        "ph": 7.3,
        "timestamp": "2025-02-22T06:09:48+01:00"
    },
    {
        "id": 179,
        "temperature": 17.11,
        "humidity": 84.91,
        "co2": 690.0,
        "light": 0.0,
        "wind_speed": 0.0,
        "moisture1": 98.77,
        "moisture2": 0.0,
        "moisture3": 95.47,
        "moisture4": 0.0,
        "nitrogen": 0.76,
        "phosphorus": 4.97,
        "potassium": 4.28,
        "ec": 915.0,
        "ph": 7.8,
        "timestamp": "2025-02-22T06:19:48+01:00"
    },
    {
        "id": 180,
        "temperature": 17.14,
        "humidity": 84.86,
        "co2": 694.0,
        "light": 0.0,
        "wind_speed": 0.0,
        "moisture1": 97.88,
        "moisture2": 0.0,
        "moisture3": 97.0,
        "moisture4": 0.0,
        "nitrogen": 0.71,
        "phosphorus": 4.93,
        "potassium": 4.36,
        "ec": 919.0,
        "ph": 7.8,
        "timestamp": "2025-02-22T06:29:48+01:00"
    },
    {
        "id": 181,
        "temperature": 17.09,
        "humidity": 84.96,
        "co2": 695.0,
        "light": 0.0,
        "wind_speed": 0.0,
        "moisture1": 97.59,
        "moisture2": 0.0,
        "moisture3": 98.94,
        "moisture4": 0.0,
        "nitrogen": 0.72,
        "phosphorus": 4.96,
        "potassium": 4.32,
        "ec": 914.0,
        "ph": 7.4,
        "timestamp": "2025-02-22T06:39:48+01:00"
    },
    {
        "id": 182,
        "temperature": 17.09,
        "humidity": 85.03,
        "co2": 700.0,
        "light": 0.0,
        "wind_speed": 0.0,
        "moisture1": 99.47,
        "moisture2": 0.0,
        "moisture3": 99.12,
        "moisture4": 0.0,
        "nitrogen": 0.5,
        "phosphorus": 5.04,
        "potassium": 4.46,
        "ec": 918.0,
        "ph": 8.0,
        "timestamp": "2025-02-22T06:49:48+01:00"
    },
    {
        "id": 183,
        "temperature": 17.07,
        "humidity": 85.02,
        "co2": 701.0,
        "light": 0.0,
        "wind_speed": 0.0,
        "moisture1": 97.59,
        "moisture2": 0.0,
        "moisture3": 97.12,
        "moisture4": 0.0,
        "nitrogen": 0.72,
        "phosphorus": 5.04,
        "potassium": 4.24,
        "ec": 919.0,
        "ph": 7.7,
        "timestamp": "2025-02-22T06:59:48+01:00"
    },
    {
        "id": 178,
        "temperature": 17.12,
        "humidity": 84.92,
        "co2": 686.0,
        "light": 0.0,
        "wind_speed": 0.0,
        "moisture1": 97.24,
        "moisture2": 0.0,
        "moisture3": 96.88,
        "moisture4": 0.0,
        "nitrogen": 0.71,
        "phosphorus": 4.93,
        "potassium": 4.36,
        "ec": 917.0,
        "ph": 7.3,
        "timestamp": "2025-02-22T06:09:48+01:00"
    },
    {
        "id": 179,
        "temperature": 17.11,
        "humidity": 84.91,
        "co2": 690.0,
        "light": 0.0,
        "wind_speed": 0.0,
        "moisture1": 98.77,
        "moisture2": 0.0,
        "moisture3": 95.47,
        "moisture4": 0.0,
        "nitrogen": 0.76,
        "phosphorus": 4.97,
        "potassium": 4.28,
        "ec": 915.0,
        "ph": 7.8,
        "timestamp": "2025-02-22T06:19:48+01:00"
    },
    {
        "id": 180,
        "temperature": 17.14,
        "humidity": 84.86,
        "co2": 694.0,
        "light": 0.0,
        "wind_speed": 0.0,
        "moisture1": 97.88,
        "moisture2": 0.0,
        "moisture3": 97.0,
        "moisture4": 0.0,
        "nitrogen": 0.71,
        "phosphorus": 4.93,
        "potassium": 4.36,
        "ec": 919.0,
        "ph": 7.8,
        "timestamp": "2025-02-22T06:29:48+01:00"
    },
    {
        "id": 181,
        "temperature": 17.09,
        "humidity": 84.96,
        "co2": 695.0,
        "light": 0.0,
        "wind_speed": 0.0,
        "moisture1": 97.59,
        "moisture2": 0.0,
        "moisture3": 98.94,
        "moisture4": 0.0,
        "nitrogen": 0.72,
        "phosphorus": 4.96,
        "potassium": 4.32,
        "ec": 914.0,
        "ph": 7.4,
        "timestamp": "2025-02-22T06:39:48+01:00"
    },
    {
        "id": 182,
        "temperature": 17.09,
        "humidity": 85.03,
        "co2": 700.0,
        "light": 0.0,
        "wind_speed": 0.0,
        "moisture1": 99.47,
        "moisture2": 0.0,
        "moisture3": 99.12,
        "moisture4": 0.0,
        "nitrogen": 0.5,
        "phosphorus": 5.04,
        "potassium": 4.46,
        "ec": 918.0,
        "ph": 8.0,
        "timestamp": "2025-02-22T06:49:48+01:00"
    },
    {
        "id": 183,
        "temperature": 17.07,
        "humidity": 85.02,
        "co2": 701.0,
        "light": 0.0,
        "wind_speed": 0.0,
        "moisture1": 97.59,
        "moisture2": 0.0,
        "moisture3": 97.12,
        "moisture4": 0.0,
        "nitrogen": 0.72,
        "phosphorus": 5.04,
        "potassium": 4.24,
        "ec": 919.0,
        "ph": 7.7,
        "timestamp": "2025-02-22T06:59:48+01:00"
    },
    {
        "id": 178,
        "temperature": 17.12,
        "humidity": 84.92,
        "co2": 686.0,
        "light": 0.0,
        "wind_speed": 0.0,
        "moisture1": 97.24,
        "moisture2": 0.0,
        "moisture3": 96.88,
        "moisture4": 0.0,
        "nitrogen": 0.71,
        "phosphorus": 4.93,
        "potassium": 4.36,
        "ec": 917.0,
        "ph": 7.3,
        "timestamp": "2025-02-22T06:09:48+01:00"
    },
    {
        "id": 179,
        "temperature": 17.11,
        "humidity": 84.91,
        "co2": 690.0,
        "light": 0.0,
        "wind_speed": 0.0,
        "moisture1": 98.77,
        "moisture2": 0.0,
        "moisture3": 95.47,
        "moisture4": 0.0,
        "nitrogen": 0.76,
        "phosphorus": 4.97,
        "potassium": 4.28,
        "ec": 915.0,
        "ph": 7.8,
        "timestamp": "2025-02-22T06:19:48+01:00"
    },
    {
        "id": 180,
        "temperature": 17.14,
        "humidity": 84.86,
        "co2": 694.0,
        "light": 0.0,
        "wind_speed": 0.0,
        "moisture1": 97.88,
        "moisture2": 0.0,
        "moisture3": 97.0,
        "moisture4": 0.0,
        "nitrogen": 0.71,
        "phosphorus": 4.93,
        "potassium": 4.36,
        "ec": 919.0,
        "ph": 7.8,
        "timestamp": "2025-02-22T06:29:48+01:00"
    },
    {
        "id": 181,
        "temperature": 17.09,
        "humidity": 84.96,
        "co2": 695.0,
        "light": 0.0,
        "wind_speed": 0.0,
        "moisture1": 97.59,
        "moisture2": 0.0,
        "moisture3": 98.94,
        "moisture4": 0.0,
        "nitrogen": 0.72,
        "phosphorus": 4.96,
        "potassium": 4.32,
        "ec": 914.0,
        "ph": 7.4,
        "timestamp": "2025-02-22T06:39:48+01:00"
    },
    {
        "id": 182,
        "temperature": 17.09,
        "humidity": 85.03,
        "co2": 700.0,
        "light": 0.0,
        "wind_speed": 0.0,
        "moisture1": 99.47,
        "moisture2": 0.0,
        "moisture3": 99.12,
        "moisture4": 0.0,
        "nitrogen": 0.5,
        "phosphorus": 5.04,
        "potassium": 4.46,
        "ec": 918.0,
        "ph": 8.0,
        "timestamp": "2025-02-22T06:49:48+01:00"
    },
    {
        "id": 183,
        "temperature": 17.07,
        "humidity": 85.02,
        "co2": 701.0,
        "light": 0.0,
        "wind_speed": 0.0,
        "moisture1": 97.59,
        "moisture2": 0.0,
        "moisture3": 97.12,
        "moisture4": 0.0,
        "nitrogen": 0.72,
        "phosphorus": 5.04,
        "potassium": 4.24,
        "ec": 919.0,
        "ph": 7.7,
        "timestamp": "2025-02-22T06:59:48+01:00"
    },
    {
        "id": 178,
        "temperature": 17.12,
        "humidity": 84.92,
        "co2": 686.0,
        "light": 0.0,
        "wind_speed": 0.0,
        "moisture1": 97.24,
        "moisture2": 0.0,
        "moisture3": 96.88,
        "moisture4": 0.0,
        "nitrogen": 0.71,
        "phosphorus": 4.93,
        "potassium": 4.36,
        "ec": 917.0,
        "ph": 7.3,
        "timestamp": "2025-02-22T06:09:48+01:00"
    },
    {
        "id": 179,
        "temperature": 17.11,
        "humidity": 84.91,
        "co2": 690.0,
        "light": 0.0,
        "wind_speed": 0.0,
        "moisture1": 98.77,
        "moisture2": 0.0,
        "moisture3": 95.47,
        "moisture4": 0.0,
        "nitrogen": 0.76,
        "phosphorus": 4.97,
        "potassium": 4.28,
        "ec": 915.0,
        "ph": 7.8,
        "timestamp": "2025-02-22T06:19:48+01:00"
    },
    {
        "id": 180,
        "temperature": 17.14,
        "humidity": 84.86,
        "co2": 694.0,
        "light": 0.0,
        "wind_speed": 0.0,
        "moisture1": 97.88,
        "moisture2": 0.0,
        "moisture3": 97.0,
        "moisture4": 0.0,
        "nitrogen": 0.71,
        "phosphorus": 4.93,
        "potassium": 4.36,
        "ec": 919.0,
        "ph": 7.8,
        "timestamp": "2025-02-22T06:29:48+01:00"
    },
    {
        "id": 181,
        "temperature": 17.09,
        "humidity": 84.96,
        "co2": 695.0,
        "light": 0.0,
        "wind_speed": 0.0,
        "moisture1": 97.59,
        "moisture2": 0.0,
        "moisture3": 98.94,
        "moisture4": 0.0,
        "nitrogen": 0.72,
        "phosphorus": 4.96,
        "potassium": 4.32,
        "ec": 914.0,
        "ph": 7.4,
        "timestamp": "2025-02-22T06:39:48+01:00"
    },
    {
        "id": 182,
        "temperature": 17.09,
        "humidity": 85.03,
        "co2": 700.0,
        "light": 0.0,
        "wind_speed": 0.0,
        "moisture1": 99.47,
        "moisture2": 0.0,
        "moisture3": 99.12,
        "moisture4": 0.0,
        "nitrogen": 0.5,
        "phosphorus": 5.04,
        "potassium": 4.46,
        "ec": 918.0,
        "ph": 8.0,
        "timestamp": "2025-02-22T06:49:48+01:00"
    },
    {
        "id": 183,
        "temperature": 17.07,
        "humidity": 85.02,
        "co2": 701.0,
        "light": 0.0,
        "wind_speed": 0.0,
        "moisture1": 97.59,
        "moisture2": 0.0,
        "moisture3": 97.12,
        "moisture4": 0.0,
        "nitrogen": 0.72,
        "phosphorus": 5.04,
        "potassium": 4.24,
        "ec": 919.0,
        "ph": 7.7,
        "timestamp": "2025-02-22T06:59:48+01:00"
    },
    {
        "id": 178,
        "temperature": 17.12,
        "humidity": 84.92,
        "co2": 686.0,
        "light": 0.0,
        "wind_speed": 0.0,
        "moisture1": 97.24,
        "moisture2": 0.0,
        "moisture3": 96.88,
        "moisture4": 0.0,
        "nitrogen": 0.71,
        "phosphorus": 4.93,
        "potassium": 4.36,
        "ec": 917.0,
        "ph": 7.3,
        "timestamp": "2025-02-22T06:09:48+01:00"
    },
    {
        "id": 179,
        "temperature": 17.11,
        "humidity": 84.91,
        "co2": 690.0,
        "light": 0.0,
        "wind_speed": 0.0,
        "moisture1": 98.77,
        "moisture2": 0.0,
        "moisture3": 95.47,
        "moisture4": 0.0,
        "nitrogen": 0.76,
        "phosphorus": 4.97,
        "potassium": 4.28,
        "ec": 915.0,
        "ph": 7.8,
        "timestamp": "2025-02-22T06:19:48+01:00"
    },
    {
        "id": 180,
        "temperature": 17.14,
        "humidity": 84.86,
        "co2": 694.0,
        "light": 0.0,
        "wind_speed": 0.0,
        "moisture1": 97.88,
        "moisture2": 0.0,
        "moisture3": 97.0,
        "moisture4": 0.0,
        "nitrogen": 0.71,
        "phosphorus": 4.93,
        "potassium": 4.36,
        "ec": 919.0,
        "ph": 7.8,
        "timestamp": "2025-02-22T06:29:48+01:00"
    },
    {
        "id": 181,
        "temperature": 17.09,
        "humidity": 84.96,
        "co2": 695.0,
        "light": 0.0,
        "wind_speed": 0.0,
        "moisture1": 97.59,
        "moisture2": 0.0,
        "moisture3": 98.94,
        "moisture4": 0.0,
        "nitrogen": 0.72,
        "phosphorus": 4.96,
        "potassium": 4.32,
        "ec": 914.0,
        "ph": 7.4,
        "timestamp": "2025-02-22T06:39:48+01:00"
    },
    {
        "id": 182,
        "temperature": 17.09,
        "humidity": 85.03,
        "co2": 700.0,
        "light": 0.0,
        "wind_speed": 0.0,
        "moisture1": 99.47,
        "moisture2": 0.0,
        "moisture3": 99.12,
        "moisture4": 0.0,
        "nitrogen": 0.5,
        "phosphorus": 5.04,
        "potassium": 4.46,
        "ec": 918.0,
        "ph": 8.0,
        "timestamp": "2025-02-22T06:49:48+01:00"
    },
    {
        "id": 183,
        "temperature": 17.07,
        "humidity": 85.02,
        "co2": 701.0,
        "light": 0.0,
        "wind_speed": 0.0,
        "moisture1": 97.59,
        "moisture2": 0.0,
        "moisture3": 97.12,
        "moisture4": 0.0,
        "nitrogen": 0.72,
        "phosphorus": 5.04,
        "potassium": 4.24,
        "ec": 919.0,
        "ph": 7.7,
        "timestamp": "2025-02-22T06:59:48+01:00"
    },
    {
        "id": 178,
        "temperature": 17.12,
        "humidity": 84.92,
        "co2": 686.0,
        "light": 0.0,
        "wind_speed": 0.0,
        "moisture1": 97.24,
        "moisture2": 0.0,
        "moisture3": 96.88,
        "moisture4": 0.0,
        "nitrogen": 0.71,
        "phosphorus": 4.93,
        "potassium": 4.36,
        "ec": 917.0,
        "ph": 7.3,
        "timestamp": "2025-02-22T06:09:48+01:00"
    },
    {
        "id": 179,
        "temperature": 17.11,
        "humidity": 84.91,
        "co2": 690.0,
        "light": 0.0,
        "wind_speed": 0.0,
        "moisture1": 98.77,
        "moisture2": 0.0,
        "moisture3": 95.47,
        "moisture4": 0.0,
        "nitrogen": 0.76,
        "phosphorus": 4.97,
        "potassium": 4.28,
        "ec": 915.0,
        "ph": 7.8,
        "timestamp": "2025-02-22T06:19:48+01:00"
    },
    {
        "id": 180,
        "temperature": 17.14,
        "humidity": 84.86,
        "co2": 694.0,
        "light": 0.0,
        "wind_speed": 0.0,
        "moisture1": 97.88,
        "moisture2": 0.0,
        "moisture3": 97.0,
        "moisture4": 0.0,
        "nitrogen": 0.71,
        "phosphorus": 4.93,
        "potassium": 4.36,
        "ec": 919.0,
        "ph": 7.8,
        "timestamp": "2025-02-22T06:29:48+01:00"
    },
    {
        "id": 181,
        "temperature": 17.09,
        "humidity": 84.96,
        "co2": 695.0,
        "light": 0.0,
        "wind_speed": 0.0,
        "moisture1": 97.59,
        "moisture2": 0.0,
        "moisture3": 98.94,
        "moisture4": 0.0,
        "nitrogen": 0.72,
        "phosphorus": 4.96,
        "potassium": 4.32,
        "ec": 914.0,
        "ph": 7.4,
        "timestamp": "2025-02-22T06:39:48+01:00"
    },
    {
        "id": 182,
        "temperature": 17.09,
        "humidity": 85.03,
        "co2": 700.0,
        "light": 0.0,
        "wind_speed": 0.0,
        "moisture1": 99.47,
        "moisture2": 0.0,
        "moisture3": 99.12,
        "moisture4": 0.0,
        "nitrogen": 0.5,
        "phosphorus": 5.04,
        "potassium": 4.46,
        "ec": 918.0,
        "ph": 8.0,
        "timestamp": "2025-02-22T06:49:48+01:00"
    },
    {
        "id": 183,
        "temperature": 17.07,
        "humidity": 85.02,
        "co2": 701.0,
        "light": 0.0,
        "wind_speed": 0.0,
        "moisture1": 97.59,
        "moisture2": 0.0,
        "moisture3": 97.12,
        "moisture4": 0.0,
        "nitrogen": 0.72,
        "phosphorus": 5.04,
        "potassium": 4.24,
        "ec": 919.0,
        "ph": 7.7,
        "timestamp": "2025-02-22T06:59:48+01:00"
    },
    {
        "id": 178,
        "temperature": 17.12,
        "humidity": 84.92,
        "co2": 686.0,
        "light": 0.0,
        "wind_speed": 0.0,
        "moisture1": 97.24,
        "moisture2": 0.0,
        "moisture3": 96.88,
        "moisture4": 0.0,
        "nitrogen": 0.71,
        "phosphorus": 4.93,
        "potassium": 4.36,
        "ec": 917.0,
        "ph": 7.3,
        "timestamp": "2025-02-22T06:09:48+01:00"
    },
    {
        "id": 179,
        "temperature": 17.11,
        "humidity": 84.91,
        "co2": 690.0,
        "light": 0.0,
        "wind_speed": 0.0,
        "moisture1": 98.77,
        "moisture2": 0.0,
        "moisture3": 95.47,
        "moisture4": 0.0,
        "nitrogen": 0.76,
        "phosphorus": 4.97,
        "potassium": 4.28,
        "ec": 915.0,
        "ph": 7.8,
        "timestamp": "2025-02-22T06:19:48+01:00"
    },
    {
        "id": 180,
        "temperature": 17.14,
        "humidity": 84.86,
        "co2": 694.0,
        "light": 0.0,
        "wind_speed": 0.0,
        "moisture1": 97.88,
        "moisture2": 0.0,
        "moisture3": 97.0,
        "moisture4": 0.0,
        "nitrogen": 0.71,
        "phosphorus": 4.93,
        "potassium": 4.36,
        "ec": 919.0,
        "ph": 7.8,
        "timestamp": "2025-02-22T06:29:48+01:00"
    },
    {
        "id": 181,
        "temperature": 17.09,
        "humidity": 84.96,
        "co2": 695.0,
        "light": 0.0,
        "wind_speed": 0.0,
        "moisture1": 97.59,
        "moisture2": 0.0,
        "moisture3": 98.94,
        "moisture4": 0.0,
        "nitrogen": 0.72,
        "phosphorus": 4.96,
        "potassium": 4.32,
        "ec": 914.0,
        "ph": 7.4,
        "timestamp": "2025-02-22T06:39:48+01:00"
    },
    {
        "id": 182,
        "temperature": 17.09,
        "humidity": 85.03,
        "co2": 700.0,
        "light": 0.0,
        "wind_speed": 0.0,
        "moisture1": 99.47,
        "moisture2": 0.0,
        "moisture3": 99.12,
        "moisture4": 0.0,
        "nitrogen": 0.5,
        "phosphorus": 5.04,
        "potassium": 4.46,
        "ec": 918.0,
        "ph": 8.0,
        "timestamp": "2025-02-22T06:49:48+01:00"
    },
    {
        "id": 183,
        "temperature": 17.07,
        "humidity": 85.02,
        "co2": 701.0,
        "light": 0.0,
        "wind_speed": 0.0,
        "moisture1": 97.59,
        "moisture2": 0.0,
        "moisture3": 97.12,
        "moisture4": 0.0,
        "nitrogen": 0.72,
        "phosphorus": 5.04,
        "potassium": 4.24,
        "ec": 919.0,
        "ph": 7.7,
        "timestamp": "2025-02-22T06:59:48+01:00"
    }
]