[
    {
        "id": 2488,
        "temperature": 26.58,
        "humidity": 68.93,
        "co2": 732.0,
        "light": 15.42,
        "wind_speed": 0.0,
        "moisture1": 83.54,
        "moisture2": 82.83,
        "moisture3": 99.94,
        "moisture4": 100.0,
        "nitrogen": 3.96,
        "phosphorus": 2.55,
        "potassium": 3.49,
        "ec": 1302.0,
        "ph": 9.0,
        "timestamp": "2025-05-10T19:00:10+02:00"
    },
    {
        "id": 2489,
        "temperature": 26.61,
        "humidity": 69.01,
        "co2": 733.0,
        "light": 12.5,
        "wind_speed": 0.0,
        "moisture1": 83.19,
        "moisture2": 82.36,
        "moisture3": 99.24,
        "moisture4": 99.24,
        "nitrogen": 4.01,
        "phosphorus": 2.6,
        "potassium": 3.39,
        "ec": 1307.0,
        "ph": 7.0,
        "timestamp": "2025-05-10T19:10:12+02:00"
    },
    {
        "id": 2490,
        "temperature": 26.66,
        "humidity": 69.03,
        "co2": 733.0,
        "light": 10.0,
        "wind_speed": 0.0,
        "moisture1": 81.78,
        "moisture2": 82.77,
        "moisture3": 100.0,
        "moisture4": 89.95,
        "nitrogen": 4.1,
        "phosphorus": 2.48,
        "potassium": 3.42,
        "ec": 1305.0,
        "ph": 5.9,
        "timestamp": "2025-05-10T19:20:10+02:00"
    },
    {
        "id": 2491,
        "temperature": 26.62,
        "humidity": 69.27,
        "co2": 758.0,
        "light": 8.33,
        "wind_speed": 0.0,
        "moisture1": 87.95,
        "moisture2": 84.48,
        "moisture3": 100.0,
        "moisture4": 100.0,
        "nitrogen": 4.1,
        "phosphorus": 2.56,
        "potassium": 3.34,
        "ec": 1300.0,
        "ph": 5.6,
        "timestamp": "2025-05-10T19:30:10+02:00"
    },
    {
        "id": 2492,
        "temperature": 26.63,
        "humidity": 69.44,
        "co2": 774.0,
        "light": 6.25,
        "wind_speed": 0.0,
        "moisture1": 82.77,
        "moisture2": 84.71,
        "moisture3": 100.0,
        "moisture4": 100.0,
        "nitrogen": 3.92,
        "phosphorus": 2.6,
        "potassium": 3.49,
        "ec": 1294.0,
        "ph": 8.5,
        "timestamp": "2025-05-10T19:40:10+02:00"
    }
]