[
    {
        "id": 1097,
        "temperature": 19.28,
        "humidity": 85.11,
        "co2": 578.0,
        "light": 3.75,
        "wind_speed": 0.0,
        "moisture1": 31.1,
        "moisture2": 46.74,
        "moisture3": 100.0,
        "moisture4": 26.22,
        "nitrogen": 3.25,
        "phosphorus": 3.29,
        "potassium": 3.45,
        "ec": 1211.0,
        "ph": 7.8,
        "timestamp": "2025-03-26T18:05:08+01:00"
    },
    {
        "id": 1098,
        "temperature": 19.28,
        "humidity": 85.26,
        "co2": 586.0,
        "light": 2.08,
        "wind_speed": 0.0,
        "moisture1": 33.57,
        "moisture2": 51.03,
        "moisture3": 100.0,
        "moisture4": 27.51,
        "nitrogen": 3.28,
        "phosphorus": 3.42,
        "potassium": 3.3,
        "ec": 1211.0,
        "ph": 7.8,
        "timestamp": "2025-03-26T18:15:08+01:00"
    },
    {
        "id": 1099,
        "temperature": 19.28,
        "humidity": 85.41,
        "co2": 592.0,
        "light": 1.25,
        "wind_speed": 0.0,
        "moisture1": 29.04,
        "moisture2": 45.91,
        "moisture3": 100.0,
        "moisture4": 28.75,
        "nitrogen": 3.27,
        "phosphorus": 3.43,
        "potassium": 3.31,
        "ec": 1211.0,
        "ph": 7.8,
        "timestamp": "2025-03-26T18:25:09+01:00"
    },
    {
        "id": 1100,
        "temperature": 19.3,
        "humidity": 85.54,
        "co2": 615.0,
        "light": 0.42,
        "wind_speed": 0.0,
        "moisture1": 33.16,
        "moisture2": 49.32,
        "moisture3": 100.0,
        "moisture4": 25.4,
        "nitrogen": 3.35,
        "phosphorus": 3.49,
        "potassium": 3.15,
        "ec": 1207.0,
        "ph": 7.8,
        "timestamp": "2025-03-26T18:35:10+01:00"
    }
]