[
    {
        "id": 3672,
        "temperature": 26.34,
        "humidity": 71.08,
        "co2": 647.0,
        "light": 73.75,
        "wind_speed": 0.0,
        "moisture1": 71.55,
        "moisture2": 93.12,
        "moisture3": 99.24,
        "moisture4": 93.53,
        "nitrogen": 0.19,
        "phosphorus": 4.44,
        "potassium": 5.37,
        "ec": 258.0,
        "ph": 8.3,
        "timestamp": "2025-05-28T11:09:09+02:00"
    },
    {
        "id": 3673,
        "temperature": 26.0,
        "humidity": 65.91,
        "co2": 400.0,
        "light": 66.25,
        "wind_speed": 0.0,
        "moisture1": 65.31,
        "moisture2": 83.72,
        "moisture3": 94.18,
        "moisture4": 92.83,
        "nitrogen": 0.19,
        "phosphorus": 4.43,
        "potassium": 5.38,
        "ec": 258.0,
        "ph": 8.3,
        "timestamp": "2025-05-28T11:19:09+02:00"
    },
    {
        "id": 3674,
        "temperature": 25.89,
        "humidity": 65.58,
        "co2": 400.0,
        "light": 58.33,
        "wind_speed": 0.0,
        "moisture1": 78.01,
        "moisture2": 98.94,
        "moisture3": 100.0,
        "moisture4": 99.65,
        "nitrogen": 0.19,
        "phosphorus": 4.43,
        "potassium": 5.38,
        "ec": 258.0,
        "ph": 8.3,
        "timestamp": "2025-05-28T11:29:09+02:00"
    },
    {
        "id": 3675,
        "temperature": 0.0,
        "humidity": 0.0,
        "co2": 400.0,
        "light": 55.83,
        "wind_speed": 0.1,
        "moisture1": 100.0,
        "moisture2": 100.0,
        "moisture3": 100.0,
        "moisture4": 100.0,
        "nitrogen": 0.19,
        "phosphorus": 4.43,
        "potassium": 5.38,
        "ec": 21556.0,
        "ph": 7.0,
        "timestamp": "2025-05-28T11:39:17+02:00"
    },
    {
        "id": 3676,
        "temperature": 0.0,
        "humidity": 0.0,
        "co2": 400.0,
        "light": 51.67,
        "wind_speed": 0.0,
        "moisture1": 100.0,
        "moisture2": 100.0,
        "moisture3": 100.0,
        "moisture4": 100.0,
        "nitrogen": 0.19,
        "phosphorus": 4.42,
        "potassium": 5.39,
        "ec": 65535.0,
        "ph": 7.0,
        "timestamp": "2025-05-28T11:49:17+02:00"
    }
]