[
    {
        "id": 556,
        "temperature": 21.33,
        "humidity": 76.55,
        "co2": 640.0,
        "light": 107.92,
        "wind_speed": 0.0,
        "moisture1": 27.87,
        "moisture2": 100.0,
        "moisture3": 100.0,
        "moisture4": 32.86,
        "nitrogen": 1.01,
        "phosphorus": 7.8,
        "potassium": 1.19,
        "ec": 1255.0,
        "ph": 7.3,
        "timestamp": "2025-04-13T10:00:09+02:00"
    },
    {
        "id": 557,
        "temperature": 21.4,
        "humidity": 76.62,
        "co2": 653.0,
        "light": 104.17,
        "wind_speed": 0.0,
        "moisture1": 28.57,
        "moisture2": 99.88,
        "moisture3": 100.0,
        "moisture4": 32.16,
        "nitrogen": 1.01,
        "phosphorus": 7.77,
        "potassium": 1.22,
        "ec": 1255.0,
        "ph": 7.3,
        "timestamp": "2025-04-13T10:10:08+02:00"
    },
    {
        "id": 558,
        "temperature": 21.4,
        "humidity": 76.19,
        "co2": 656.0,
        "light": 94.58,
        "wind_speed": 0.0,
        "moisture1": 27.98,
        "moisture2": 100.0,
        "moisture3": 100.0,
        "moisture4": 33.51,
        "nitrogen": 1.02,
        "phosphorus": 7.78,
        "potassium": 1.2,
        "ec": 1263.0,
        "ph": 7.4,
        "timestamp": "2025-04-13T10:20:08+02:00"
    },
    {
        "id": 559,
        "temperature": 21.43,
        "humidity": 75.86,
        "co2": 628.0,
        "light": 87.08,
        "wind_speed": 0.0,
        "moisture1": 26.4,
        "moisture2": 99.53,
        "moisture3": 100.0,
        "moisture4": 31.98,
        "nitrogen": 1.0,
        "phosphorus": 7.81,
        "potassium": 1.19,
        "ec": 1258.0,
        "ph": 7.4,
        "timestamp": "2025-04-13T10:30:08+02:00"
    }
]