[
    {
        "id": 1617,
        "temperature": 19.07,
        "humidity": 77.86,
        "co2": 386.0,
        "light": 61.25,
        "wind_speed": 0.0,
        "moisture1": 52.62,
        "moisture2": 100.0,
        "moisture3": 100.0,
        "moisture4": 61.61,
        "nitrogen": 1.03,
        "phosphorus": 7.77,
        "potassium": 1.2,
        "ec": 1044.0,
        "ph": 7.0,
        "timestamp": "2025-04-03T13:04:08+02:00"
    },
    {
        "id": 1618,
        "temperature": 19.09,
        "humidity": 77.87,
        "co2": 381.0,
        "light": 74.17,
        "wind_speed": 0.0,
        "moisture1": 50.03,
        "moisture2": 100.0,
        "moisture3": 100.0,
        "moisture4": 63.08,
        "nitrogen": 1.03,
        "phosphorus": 7.71,
        "potassium": 1.25,
        "ec": 1046.0,
        "ph": 7.1,
        "timestamp": "2025-04-03T13:14:08+02:00"
    },
    {
        "id": 1619,
        "temperature": 19.1,
        "humidity": 77.79,
        "co2": 374.0,
        "light": 67.92,
        "wind_speed": 0.0,
        "moisture1": 51.03,
        "moisture2": 100.0,
        "moisture3": 100.0,
        "moisture4": 61.08,
        "nitrogen": 1.01,
        "phosphorus": 7.8,
        "potassium": 1.19,
        "ec": 1043.0,
        "ph": 7.1,
        "timestamp": "2025-04-03T13:24:07+02:00"
    },
    {
        "id": 1620,
        "temperature": 19.11,
        "humidity": 77.83,
        "co2": 388.0,
        "light": 95.0,
        "wind_speed": 0.0,
        "moisture1": 47.5,
        "moisture2": 99.35,
        "moisture3": 100.0,
        "moisture4": 60.61,
        "nitrogen": 1.01,
        "phosphorus": 7.78,
        "potassium": 1.21,
        "ec": 1045.0,
        "ph": 7.1,
        "timestamp": "2025-04-03T13:34:07+02:00"
    },
    {
        "id": 1621,
        "temperature": 19.17,
        "humidity": 77.79,
        "co2": 375.0,
        "light": 99.58,
        "wind_speed": 0.0,
        "moisture1": 45.8,
        "moisture2": 97.06,
        "moisture3": 100.0,
        "moisture4": 58.85,
        "nitrogen": 1.0,
        "phosphorus": 7.82,
        "potassium": 1.18,
        "ec": 1051.0,
        "ph": 7.1,
        "timestamp": "2025-04-03T13:44:07+02:00"
    }
]