[
    {
        "id": 3685,
        "temperature": 26.36,
        "humidity": 68.8,
        "co2": 599.0,
        "light": 17.5,
        "wind_speed": 0.0,
        "moisture1": 87.01,
        "moisture2": 98.59,
        "moisture3": 94.53,
        "moisture4": 88.42,
        "nitrogen": 0.83,
        "phosphorus": 4.01,
        "potassium": 5.16,
        "ec": 311.0,
        "ph": 8.1,
        "timestamp": "2025-05-30T12:02:10+02:00"
    },
    {
        "id": 3686,
        "temperature": 26.41,
        "humidity": 69.29,
        "co2": 634.0,
        "light": 17.08,
        "wind_speed": 0.0,
        "moisture1": 86.18,
        "moisture2": 98.82,
        "moisture3": 92.48,
        "moisture4": 86.36,
        "nitrogen": 0.83,
        "phosphorus": 3.99,
        "potassium": 5.18,
        "ec": 312.0,
        "ph": 8.1,
        "timestamp": "2025-05-30T12:12:10+02:00"
    },
    {
        "id": 3687,
        "temperature": 26.43,
        "humidity": 69.29,
        "co2": 611.0,
        "light": 16.67,
        "wind_speed": 0.0,
        "moisture1": 86.36,
        "moisture2": 98.77,
        "moisture3": 92.53,
        "moisture4": 84.13,
        "nitrogen": 0.84,
        "phosphorus": 4.0,
        "potassium": 5.16,
        "ec": 312.0,
        "ph": 8.1,
        "timestamp": "2025-05-30T12:22:10+02:00"
    },
    {
        "id": 3688,
        "temperature": 26.48,
        "humidity": 68.9,
        "co2": 611.0,
        "light": 16.67,
        "wind_speed": 0.0,
        "moisture1": 88.59,
        "moisture2": 100.0,
        "moisture3": 95.24,
        "moisture4": 100.0,
        "nitrogen": 0.83,
        "phosphorus": 4.0,
        "potassium": 5.17,
        "ec": 312.0,
        "ph": 8.3,
        "timestamp": "2025-05-30T12:32:10+02:00"
    },
    {
        "id": 3689,
        "temperature": 26.46,
        "humidity": 68.5,
        "co2": 601.0,
        "light": 16.25,
        "wind_speed": 0.0,
        "moisture1": 86.24,
        "moisture2": 98.35,
        "moisture3": 93.83,
        "moisture4": 100.0,
        "nitrogen": 0.84,
        "phosphorus": 4.0,
        "potassium": 5.16,
        "ec": 313.0,
        "ph": 8.2,
        "timestamp": "2025-05-30T12:42:10+02:00"
    }
]