[
    {
        "id": 283,
        "temperature": 17.34,
        "humidity": 80.81,
        "co2": 480.0,
        "light": 0.0,
        "wind_speed": 0.0,
        "moisture1": 100.0,
        "moisture2": 98.77,
        "moisture3": 100.0,
        "moisture4": 100.0,
        "nitrogen": 1.3,
        "phosphorus": 4.46,
        "potassium": 4.24,
        "ec": 1340.0,
        "ph": 7.3,
        "timestamp": "2025-02-23T00:09:48+01:00"
    },
    {
        "id": 284,
        "temperature": 17.33,
        "humidity": 80.75,
        "co2": 481.0,
        "light": 0.0,
        "wind_speed": 0.0,
        "moisture1": 100.0,
        "moisture2": 98.88,
        "moisture3": 100.0,
        "moisture4": 100.0,
        "nitrogen": 1.31,
        "phosphorus": 4.53,
        "potassium": 4.16,
        "ec": 1351.0,
        "ph": 7.2,
        "timestamp": "2025-02-23T00:19:48+01:00"
    },
    {
        "id": 285,
        "temperature": 17.35,
        "humidity": 80.6,
        "co2": 486.0,
        "light": 0.0,
        "wind_speed": 0.0,
        "moisture1": 100.0,
        "moisture2": 99.0,
        "moisture3": 99.71,
        "moisture4": 100.0,
        "nitrogen": 1.31,
        "phosphorus": 4.36,
        "potassium": 4.33,
        "ec": 1336.0,
        "ph": 7.4,
        "timestamp": "2025-02-23T00:29:48+01:00"
    },
    {
        "id": 286,
        "temperature": 17.34,
        "humidity": 80.56,
        "co2": 491.0,
        "light": 0.0,
        "wind_speed": 0.0,
        "moisture1": 100.0,
        "moisture2": 99.12,
        "moisture3": 100.0,
        "moisture4": 100.0,
        "nitrogen": 1.32,
        "phosphorus": 4.46,
        "potassium": 4.22,
        "ec": 1336.0,
        "ph": 8.0,
        "timestamp": "2025-02-23T00:39:48+01:00"
    },
    {
        "id": 287,
        "temperature": 17.33,
        "humidity": 80.55,
        "co2": 491.0,
        "light": 0.0,
        "wind_speed": 0.0,
        "moisture1": 100.0,
        "moisture2": 98.77,
        "moisture3": 99.12,
        "moisture4": 100.0,
        "nitrogen": 1.3,
        "phosphorus": 4.47,
        "potassium": 4.22,
        "ec": 1331.0,
        "ph": 7.6,
        "timestamp": "2025-02-23T00:49:48+01:00"
    },
    {
        "id": 288,
        "temperature": 17.33,
        "humidity": 80.44,
        "co2": 491.0,
        "light": 0.0,
        "wind_speed": 0.0,
        "moisture1": 100.0,
        "moisture2": 99.12,
        "moisture3": 100.0,
        "moisture4": 100.0,
        "nitrogen": 1.24,
        "phosphorus": 4.52,
        "potassium": 4.24,
        "ec": 1334.0,
        "ph": 7.8,
        "timestamp": "2025-02-23T00:59:48+01:00"
    },
    {
        "id": 283,
        "temperature": 17.34,
        "humidity": 80.81,
        "co2": 480.0,
        "light": 0.0,
        "wind_speed": 0.0,
        "moisture1": 100.0,
        "moisture2": 98.77,
        "moisture3": 100.0,
        "moisture4": 100.0,
        "nitrogen": 1.3,
        "phosphorus": 4.46,
        "potassium": 4.24,
        "ec": 1340.0,
        "ph": 7.3,
        "timestamp": "2025-02-23T00:09:48+01:00"
    },
    {
        "id": 284,
        "temperature": 17.33,
        "humidity": 80.75,
        "co2": 481.0,
        "light": 0.0,
        "wind_speed": 0.0,
        "moisture1": 100.0,
        "moisture2": 98.88,
        "moisture3": 100.0,
        "moisture4": 100.0,
        "nitrogen": 1.31,
        "phosphorus": 4.53,
        "potassium": 4.16,
        "ec": 1351.0,
        "ph": 7.2,
        "timestamp": "2025-02-23T00:19:48+01:00"
    },
    {
        "id": 285,
        "temperature": 17.35,
        "humidity": 80.6,
        "co2": 486.0,
        "light": 0.0,
        "wind_speed": 0.0,
        "moisture1": 100.0,
        "moisture2": 99.0,
        "moisture3": 99.71,
        "moisture4": 100.0,
        "nitrogen": 1.31,
        "phosphorus": 4.36,
        "potassium": 4.33,
        "ec": 1336.0,
        "ph": 7.4,
        "timestamp": "2025-02-23T00:29:48+01:00"
    },
    {
        "id": 286,
        "temperature": 17.34,
        "humidity": 80.56,
        "co2": 491.0,
        "light": 0.0,
        "wind_speed": 0.0,
        "moisture1": 100.0,
        "moisture2": 99.12,
        "moisture3": 100.0,
        "moisture4": 100.0,
        "nitrogen": 1.32,
        "phosphorus": 4.46,
        "potassium": 4.22,
        "ec": 1336.0,
        "ph": 8.0,
        "timestamp": "2025-02-23T00:39:48+01:00"
    },
    {
        "id": 287,
        "temperature": 17.33,
        "humidity": 80.55,
        "co2": 491.0,
        "light": 0.0,
        "wind_speed": 0.0,
        "moisture1": 100.0,
        "moisture2": 98.77,
        "moisture3": 99.12,
        "moisture4": 100.0,
        "nitrogen": 1.3,
        "phosphorus": 4.47,
        "potassium": 4.22,
        "ec": 1331.0,
        "ph": 7.6,
        "timestamp": "2025-02-23T00:49:48+01:00"
    },
    {
        "id": 288,
        "temperature": 17.33,
        "humidity": 80.44,
        "co2": 491.0,
        "light": 0.0,
        "wind_speed": 0.0,
        "moisture1": 100.0,
        "moisture2": 99.12,
        "moisture3": 100.0,
        "moisture4": 100.0,
        "nitrogen": 1.24,
        "phosphorus": 4.52,
        "potassium": 4.24,
        "ec": 1334.0,
        "ph": 7.8,
        "timestamp": "2025-02-23T00:59:48+01:00"
    },
    {
        "id": 283,
        "temperature": 17.34,
        "humidity": 80.81,
        "co2": 480.0,
        "light": 0.0,
        "wind_speed": 0.0,
        "moisture1": 100.0,
        "moisture2": 98.77,
        "moisture3": 100.0,
        "moisture4": 100.0,
        "nitrogen": 1.3,
        "phosphorus": 4.46,
        "potassium": 4.24,
        "ec": 1340.0,
        "ph": 7.3,
        "timestamp": "2025-02-23T00:09:48+01:00"
    },
    {
        "id": 284,
        "temperature": 17.33,
        "humidity": 80.75,
        "co2": 481.0,
        "light": 0.0,
        "wind_speed": 0.0,
        "moisture1": 100.0,
        "moisture2": 98.88,
        "moisture3": 100.0,
        "moisture4": 100.0,
        "nitrogen": 1.31,
        "phosphorus": 4.53,
        "potassium": 4.16,
        "ec": 1351.0,
        "ph": 7.2,
        "timestamp": "2025-02-23T00:19:48+01:00"
    },
    {
        "id": 285,
        "temperature": 17.35,
        "humidity": 80.6,
        "co2": 486.0,
        "light": 0.0,
        "wind_speed": 0.0,
        "moisture1": 100.0,
        "moisture2": 99.0,
        "moisture3": 99.71,
        "moisture4": 100.0,
        "nitrogen": 1.31,
        "phosphorus": 4.36,
        "potassium": 4.33,
        "ec": 1336.0,
        "ph": 7.4,
        "timestamp": "2025-02-23T00:29:48+01:00"
    },
    {
        "id": 286,
        "temperature": 17.34,
        "humidity": 80.56,
        "co2": 491.0,
        "light": 0.0,
        "wind_speed": 0.0,
        "moisture1": 100.0,
        "moisture2": 99.12,
        "moisture3": 100.0,
        "moisture4": 100.0,
        "nitrogen": 1.32,
        "phosphorus": 4.46,
        "potassium": 4.22,
        "ec": 1336.0,
        "ph": 8.0,
        "timestamp": "2025-02-23T00:39:48+01:00"
    },
    {
        "id": 287,
        "temperature": 17.33,
        "humidity": 80.55,
        "co2": 491.0,
        "light": 0.0,
        "wind_speed": 0.0,
        "moisture1": 100.0,
        "moisture2": 98.77,
        "moisture3": 99.12,
        "moisture4": 100.0,
        "nitrogen": 1.3,
        "phosphorus": 4.47,
        "potassium": 4.22,
        "ec": 1331.0,
        "ph": 7.6,
        "timestamp": "2025-02-23T00:49:48+01:00"
    },
    {
        "id": 288,
        "temperature": 17.33,
        "humidity": 80.44,
        "co2": 491.0,
        "light": 0.0,
        "wind_speed": 0.0,
        "moisture1": 100.0,
        "moisture2": 99.12,
        "moisture3": 100.0,
        "moisture4": 100.0,
        "nitrogen": 1.24,
        "phosphorus": 4.52,
        "potassium": 4.24,
        "ec": 1334.0,
        "ph": 7.8,
        "timestamp": "2025-02-23T00:59:48+01:00"
    },
    {
        "id": 283,
        "temperature": 17.34,
        "humidity": 80.81,
        "co2": 480.0,
        "light": 0.0,
        "wind_speed": 0.0,
        "moisture1": 100.0,
        "moisture2": 98.77,
        "moisture3": 100.0,
        "moisture4": 100.0,
        "nitrogen": 1.3,
        "phosphorus": 4.46,
        "potassium": 4.24,
        "ec": 1340.0,
        "ph": 7.3,
        "timestamp": "2025-02-23T00:09:48+01:00"
    },
    {
        "id": 284,
        "temperature": 17.33,
        "humidity": 80.75,
        "co2": 481.0,
        "light": 0.0,
        "wind_speed": 0.0,
        "moisture1": 100.0,
        "moisture2": 98.88,
        "moisture3": 100.0,
        "moisture4": 100.0,
        "nitrogen": 1.31,
        "phosphorus": 4.53,
        "potassium": 4.16,
        "ec": 1351.0,
        "ph": 7.2,
        "timestamp": "2025-02-23T00:19:48+01:00"
    },
    {
        "id": 285,
        "temperature": 17.35,
        "humidity": 80.6,
        "co2": 486.0,
        "light": 0.0,
        "wind_speed": 0.0,
        "moisture1": 100.0,
        "moisture2": 99.0,
        "moisture3": 99.71,
        "moisture4": 100.0,
        "nitrogen": 1.31,
        "phosphorus": 4.36,
        "potassium": 4.33,
        "ec": 1336.0,
        "ph": 7.4,
        "timestamp": "2025-02-23T00:29:48+01:00"
    },
    {
        "id": 286,
        "temperature": 17.34,
        "humidity": 80.56,
        "co2": 491.0,
        "light": 0.0,
        "wind_speed": 0.0,
        "moisture1": 100.0,
        "moisture2": 99.12,
        "moisture3": 100.0,
        "moisture4": 100.0,
        "nitrogen": 1.32,
        "phosphorus": 4.46,
        "potassium": 4.22,
        "ec": 1336.0,
        "ph": 8.0,
        "timestamp": "2025-02-23T00:39:48+01:00"
    },
    {
        "id": 287,
        "temperature": 17.33,
        "humidity": 80.55,
        "co2": 491.0,
        "light": 0.0,
        "wind_speed": 0.0,
        "moisture1": 100.0,
        "moisture2": 98.77,
        "moisture3": 99.12,
        "moisture4": 100.0,
        "nitrogen": 1.3,
        "phosphorus": 4.47,
        "potassium": 4.22,
        "ec": 1331.0,
        "ph": 7.6,
        "timestamp": "2025-02-23T00:49:48+01:00"
    },
    {
        "id": 288,
        "temperature": 17.33,
        "humidity": 80.44,
        "co2": 491.0,
        "light": 0.0,
        "wind_speed": 0.0,
        "moisture1": 100.0,
        "moisture2": 99.12,
        "moisture3": 100.0,
        "moisture4": 100.0,
        "nitrogen": 1.24,
        "phosphorus": 4.52,
        "potassium": 4.24,
        "ec": 1334.0,
        "ph": 7.8,
        "timestamp": "2025-02-23T00:59:48+01:00"
    },
    {
        "id": 283,
        "temperature": 17.34,
        "humidity": 80.81,
        "co2": 480.0,
        "light": 0.0,
        "wind_speed": 0.0,
        "moisture1": 100.0,
        "moisture2": 98.77,
        "moisture3": 100.0,
        "moisture4": 100.0,
        "nitrogen": 1.3,
        "phosphorus": 4.46,
        "potassium": 4.24,
        "ec": 1340.0,
        "ph": 7.3,
        "timestamp": "2025-02-23T00:09:48+01:00"
    },
    {
        "id": 284,
        "temperature": 17.33,
        "humidity": 80.75,
        "co2": 481.0,
        "light": 0.0,
        "wind_speed": 0.0,
        "moisture1": 100.0,
        "moisture2": 98.88,
        "moisture3": 100.0,
        "moisture4": 100.0,
        "nitrogen": 1.31,
        "phosphorus": 4.53,
        "potassium": 4.16,
        "ec": 1351.0,
        "ph": 7.2,
        "timestamp": "2025-02-23T00:19:48+01:00"
    },
    {
        "id": 285,
        "temperature": 17.35,
        "humidity": 80.6,
        "co2": 486.0,
        "light": 0.0,
        "wind_speed": 0.0,
        "moisture1": 100.0,
        "moisture2": 99.0,
        "moisture3": 99.71,
        "moisture4": 100.0,
        "nitrogen": 1.31,
        "phosphorus": 4.36,
        "potassium": 4.33,
        "ec": 1336.0,
        "ph": 7.4,
        "timestamp": "2025-02-23T00:29:48+01:00"
    },
    {
        "id": 286,
        "temperature": 17.34,
        "humidity": 80.56,
        "co2": 491.0,
        "light": 0.0,
        "wind_speed": 0.0,
        "moisture1": 100.0,
        "moisture2": 99.12,
        "moisture3": 100.0,
        "moisture4": 100.0,
        "nitrogen": 1.32,
        "phosphorus": 4.46,
        "potassium": 4.22,
        "ec": 1336.0,
        "ph": 8.0,
        "timestamp": "2025-02-23T00:39:48+01:00"
    },
    {
        "id": 287,
        "temperature": 17.33,
        "humidity": 80.55,
        "co2": 491.0,
        "light": 0.0,
        "wind_speed": 0.0,
        "moisture1": 100.0,
        "moisture2": 98.77,
        "moisture3": 99.12,
        "moisture4": 100.0,
        "nitrogen": 1.3,
        "phosphorus": 4.47,
        "potassium": 4.22,
        "ec": 1331.0,
        "ph": 7.6,
        "timestamp": "2025-02-23T00:49:48+01:00"
    },
    {
        "id": 288,
        "temperature": 17.33,
        "humidity": 80.44,
        "co2": 491.0,
        "light": 0.0,
        "wind_speed": 0.0,
        "moisture1": 100.0,
        "moisture2": 99.12,
        "moisture3": 100.0,
        "moisture4": 100.0,
        "nitrogen": 1.24,
        "phosphorus": 4.52,
        "potassium": 4.24,
        "ec": 1334.0,
        "ph": 7.8,
        "timestamp": "2025-02-23T00:59:48+01:00"
    },
    {
        "id": 283,
        "temperature": 17.34,
        "humidity": 80.81,
        "co2": 480.0,
        "light": 0.0,
        "wind_speed": 0.0,
        "moisture1": 100.0,
        "moisture2": 98.77,
        "moisture3": 100.0,
        "moisture4": 100.0,
        "nitrogen": 1.3,
        "phosphorus": 4.46,
        "potassium": 4.24,
        "ec": 1340.0,
        "ph": 7.3,
        "timestamp": "2025-02-23T00:09:48+01:00"
    },
    {
        "id": 284,
        "temperature": 17.33,
        "humidity": 80.75,
        "co2": 481.0,
        "light": 0.0,
        "wind_speed": 0.0,
        "moisture1": 100.0,
        "moisture2": 98.88,
        "moisture3": 100.0,
        "moisture4": 100.0,
        "nitrogen": 1.31,
        "phosphorus": 4.53,
        "potassium": 4.16,
        "ec": 1351.0,
        "ph": 7.2,
        "timestamp": "2025-02-23T00:19:48+01:00"
    },
    {
        "id": 285,
        "temperature": 17.35,
        "humidity": 80.6,
        "co2": 486.0,
        "light": 0.0,
        "wind_speed": 0.0,
        "moisture1": 100.0,
        "moisture2": 99.0,
        "moisture3": 99.71,
        "moisture4": 100.0,
        "nitrogen": 1.31,
        "phosphorus": 4.36,
        "potassium": 4.33,
        "ec": 1336.0,
        "ph": 7.4,
        "timestamp": "2025-02-23T00:29:48+01:00"
    },
    {
        "id": 286,
        "temperature": 17.34,
        "humidity": 80.56,
        "co2": 491.0,
        "light": 0.0,
        "wind_speed": 0.0,
        "moisture1": 100.0,
        "moisture2": 99.12,
        "moisture3": 100.0,
        "moisture4": 100.0,
        "nitrogen": 1.32,
        "phosphorus": 4.46,
        "potassium": 4.22,
        "ec": 1336.0,
        "ph": 8.0,
        "timestamp": "2025-02-23T00:39:48+01:00"
    },
    {
        "id": 287,
        "temperature": 17.33,
        "humidity": 80.55,
        "co2": 491.0,
        "light": 0.0,
        "wind_speed": 0.0,
        "moisture1": 100.0,
        "moisture2": 98.77,
        "moisture3": 99.12,
        "moisture4": 100.0,
        "nitrogen": 1.3,
        "phosphorus": 4.47,
        "potassium": 4.22,
        "ec": 1331.0,
        "ph": 7.6,
        "timestamp": "2025-02-23T00:49:48+01:00"
    },
    {
        "id": 288,
        "temperature": 17.33,
        "humidity": 80.44,
        "co2": 491.0,
        "light": 0.0,
        "wind_speed": 0.0,
        "moisture1": 100.0,
        "moisture2": 99.12,
        "moisture3": 100.0,
        "moisture4": 100.0,
        "nitrogen": 1.24,
        "phosphorus": 4.52,
        "potassium": 4.24,
        "ec": 1334.0,
        "ph": 7.8,
        "timestamp": "2025-02-23T00:59:48+01:00"
    },
    {
        "id": 283,
        "temperature": 17.34,
        "humidity": 80.81,
        "co2": 480.0,
        "light": 0.0,
        "wind_speed": 0.0,
        "moisture1": 100.0,
        "moisture2": 98.77,
        "moisture3": 100.0,
        "moisture4": 100.0,
        "nitrogen": 1.3,
        "phosphorus": 4.46,
        "potassium": 4.24,
        "ec": 1340.0,
        "ph": 7.3,
        "timestamp": "2025-02-23T00:09:48+01:00"
    },
    {
        "id": 284,
        "temperature": 17.33,
        "humidity": 80.75,
        "co2": 481.0,
        "light": 0.0,
        "wind_speed": 0.0,
        "moisture1": 100.0,
        "moisture2": 98.88,
        "moisture3": 100.0,
        "moisture4": 100.0,
        "nitrogen": 1.31,
        "phosphorus": 4.53,
        "potassium": 4.16,
        "ec": 1351.0,
        "ph": 7.2,
        "timestamp": "2025-02-23T00:19:48+01:00"
    },
    {
        "id": 285,
        "temperature": 17.35,
        "humidity": 80.6,
        "co2": 486.0,
        "light": 0.0,
        "wind_speed": 0.0,
        "moisture1": 100.0,
        "moisture2": 99.0,
        "moisture3": 99.71,
        "moisture4": 100.0,
        "nitrogen": 1.31,
        "phosphorus": 4.36,
        "potassium": 4.33,
        "ec": 1336.0,
        "ph": 7.4,
        "timestamp": "2025-02-23T00:29:48+01:00"
    },
    {
        "id": 286,
        "temperature": 17.34,
        "humidity": 80.56,
        "co2": 491.0,
        "light": 0.0,
        "wind_speed": 0.0,
        "moisture1": 100.0,
        "moisture2": 99.12,
        "moisture3": 100.0,
        "moisture4": 100.0,
        "nitrogen": 1.32,
        "phosphorus": 4.46,
        "potassium": 4.22,
        "ec": 1336.0,
        "ph": 8.0,
        "timestamp": "2025-02-23T00:39:48+01:00"
    },
    {
        "id": 287,
        "temperature": 17.33,
        "humidity": 80.55,
        "co2": 491.0,
        "light": 0.0,
        "wind_speed": 0.0,
        "moisture1": 100.0,
        "moisture2": 98.77,
        "moisture3": 99.12,
        "moisture4": 100.0,
        "nitrogen": 1.3,
        "phosphorus": 4.47,
        "potassium": 4.22,
        "ec": 1331.0,
        "ph": 7.6,
        "timestamp": "2025-02-23T00:49:48+01:00"
    },
    {
        "id": 288,
        "temperature": 17.33,
        "humidity": 80.44,
        "co2": 491.0,
        "light": 0.0,
        "wind_speed": 0.0,
        "moisture1": 100.0,
        "moisture2": 99.12,
        "moisture3": 100.0,
        "moisture4": 100.0,
        "nitrogen": 1.24,
        "phosphorus": 4.52,
        "potassium": 4.24,
        "ec": 1334.0,
        "ph": 7.8,
        "timestamp": "2025-02-23T00:59:48+01:00"
    },
    {
        "id": 283,
        "temperature": 17.34,
        "humidity": 80.81,
        "co2": 480.0,
        "light": 0.0,
        "wind_speed": 0.0,
        "moisture1": 100.0,
        "moisture2": 98.77,
        "moisture3": 100.0,
        "moisture4": 100.0,
        "nitrogen": 1.3,
        "phosphorus": 4.46,
        "potassium": 4.24,
        "ec": 1340.0,
        "ph": 7.3,
        "timestamp": "2025-02-23T00:09:48+01:00"
    },
    {
        "id": 284,
        "temperature": 17.33,
        "humidity": 80.75,
        "co2": 481.0,
        "light": 0.0,
        "wind_speed": 0.0,
        "moisture1": 100.0,
        "moisture2": 98.88,
        "moisture3": 100.0,
        "moisture4": 100.0,
        "nitrogen": 1.31,
        "phosphorus": 4.53,
        "potassium": 4.16,
        "ec": 1351.0,
        "ph": 7.2,
        "timestamp": "2025-02-23T00:19:48+01:00"
    },
    {
        "id": 285,
        "temperature": 17.35,
        "humidity": 80.6,
        "co2": 486.0,
        "light": 0.0,
        "wind_speed": 0.0,
        "moisture1": 100.0,
        "moisture2": 99.0,
        "moisture3": 99.71,
        "moisture4": 100.0,
        "nitrogen": 1.31,
        "phosphorus": 4.36,
        "potassium": 4.33,
        "ec": 1336.0,
        "ph": 7.4,
        "timestamp": "2025-02-23T00:29:48+01:00"
    },
    {
        "id": 286,
        "temperature": 17.34,
        "humidity": 80.56,
        "co2": 491.0,
        "light": 0.0,
        "wind_speed": 0.0,
        "moisture1": 100.0,
        "moisture2": 99.12,
        "moisture3": 100.0,
        "moisture4": 100.0,
        "nitrogen": 1.32,
        "phosphorus": 4.46,
        "potassium": 4.22,
        "ec": 1336.0,
        "ph": 8.0,
        "timestamp": "2025-02-23T00:39:48+01:00"
    },
    {
        "id": 287,
        "temperature": 17.33,
        "humidity": 80.55,
        "co2": 491.0,
        "light": 0.0,
        "wind_speed": 0.0,
        "moisture1": 100.0,
        "moisture2": 98.77,
        "moisture3": 99.12,
        "moisture4": 100.0,
        "nitrogen": 1.3,
        "phosphorus": 4.47,
        "potassium": 4.22,
        "ec": 1331.0,
        "ph": 7.6,
        "timestamp": "2025-02-23T00:49:48+01:00"
    },
    {
        "id": 288,
        "temperature": 17.33,
        "humidity": 80.44,
        "co2": 491.0,
        "light": 0.0,
        "wind_speed": 0.0,
        "moisture1": 100.0,
        "moisture2": 99.12,
        "moisture3": 100.0,
        "moisture4": 100.0,
        "nitrogen": 1.24,
        "phosphorus": 4.52,
        "potassium": 4.24,
        "ec": 1334.0,
        "ph": 7.8,
        "timestamp": "2025-02-23T00:59:48+01:00"
    },
    {
        "id": 283,
        "temperature": 17.34,
        "humidity": 80.81,
        "co2": 480.0,
        "light": 0.0,
        "wind_speed": 0.0,
        "moisture1": 100.0,
        "moisture2": 98.77,
        "moisture3": 100.0,
        "moisture4": 100.0,
        "nitrogen": 1.3,
        "phosphorus": 4.46,
        "potassium": 4.24,
        "ec": 1340.0,
        "ph": 7.3,
        "timestamp": "2025-02-23T00:09:48+01:00"
    },
    {
        "id": 284,
        "temperature": 17.33,
        "humidity": 80.75,
        "co2": 481.0,
        "light": 0.0,
        "wind_speed": 0.0,
        "moisture1": 100.0,
        "moisture2": 98.88,
        "moisture3": 100.0,
        "moisture4": 100.0,
        "nitrogen": 1.31,
        "phosphorus": 4.53,
        "potassium": 4.16,
        "ec": 1351.0,
        "ph": 7.2,
        "timestamp": "2025-02-23T00:19:48+01:00"
    },
    {
        "id": 285,
        "temperature": 17.35,
        "humidity": 80.6,
        "co2": 486.0,
        "light": 0.0,
        "wind_speed": 0.0,
        "moisture1": 100.0,
        "moisture2": 99.0,
        "moisture3": 99.71,
        "moisture4": 100.0,
        "nitrogen": 1.31,
        "phosphorus": 4.36,
        "potassium": 4.33,
        "ec": 1336.0,
        "ph": 7.4,
        "timestamp": "2025-02-23T00:29:48+01:00"
    },
    {
        "id": 286,
        "temperature": 17.34,
        "humidity": 80.56,
        "co2": 491.0,
        "light": 0.0,
        "wind_speed": 0.0,
        "moisture1": 100.0,
        "moisture2": 99.12,
        "moisture3": 100.0,
        "moisture4": 100.0,
        "nitrogen": 1.32,
        "phosphorus": 4.46,
        "potassium": 4.22,
        "ec": 1336.0,
        "ph": 8.0,
        "timestamp": "2025-02-23T00:39:48+01:00"
    },
    {
        "id": 287,
        "temperature": 17.33,
        "humidity": 80.55,
        "co2": 491.0,
        "light": 0.0,
        "wind_speed": 0.0,
        "moisture1": 100.0,
        "moisture2": 98.77,
        "moisture3": 99.12,
        "moisture4": 100.0,
        "nitrogen": 1.3,
        "phosphorus": 4.47,
        "potassium": 4.22,
        "ec": 1331.0,
        "ph": 7.6,
        "timestamp": "2025-02-23T00:49:48+01:00"
    },
    {
        "id": 288,
        "temperature": 17.33,
        "humidity": 80.44,
        "co2": 491.0,
        "light": 0.0,
        "wind_speed": 0.0,
        "moisture1": 100.0,
        "moisture2": 99.12,
        "moisture3": 100.0,
        "moisture4": 100.0,
        "nitrogen": 1.24,
        "phosphorus": 4.52,
        "potassium": 4.24,
        "ec": 1334.0,
        "ph": 7.8,
        "timestamp": "2025-02-23T00:59:48+01:00"
    },
    {
        "id": 283,
        "temperature": 17.34,
        "humidity": 80.81,
        "co2": 480.0,
        "light": 0.0,
        "wind_speed": 0.0,
        "moisture1": 100.0,
        "moisture2": 98.77,
        "moisture3": 100.0,
        "moisture4": 100.0,
        "nitrogen": 1.3,
        "phosphorus": 4.46,
        "potassium": 4.24,
        "ec": 1340.0,
        "ph": 7.3,
        "timestamp": "2025-02-23T00:09:48+01:00"
    },
    {
        "id": 284,
        "temperature": 17.33,
        "humidity": 80.75,
        "co2": 481.0,
        "light": 0.0,
        "wind_speed": 0.0,
        "moisture1": 100.0,
        "moisture2": 98.88,
        "moisture3": 100.0,
        "moisture4": 100.0,
        "nitrogen": 1.31,
        "phosphorus": 4.53,
        "potassium": 4.16,
        "ec": 1351.0,
        "ph": 7.2,
        "timestamp": "2025-02-23T00:19:48+01:00"
    },
    {
        "id": 285,
        "temperature": 17.35,
        "humidity": 80.6,
        "co2": 486.0,
        "light": 0.0,
        "wind_speed": 0.0,
        "moisture1": 100.0,
        "moisture2": 99.0,
        "moisture3": 99.71,
        "moisture4": 100.0,
        "nitrogen": 1.31,
        "phosphorus": 4.36,
        "potassium": 4.33,
        "ec": 1336.0,
        "ph": 7.4,
        "timestamp": "2025-02-23T00:29:48+01:00"
    },
    {
        "id": 286,
        "temperature": 17.34,
        "humidity": 80.56,
        "co2": 491.0,
        "light": 0.0,
        "wind_speed": 0.0,
        "moisture1": 100.0,
        "moisture2": 99.12,
        "moisture3": 100.0,
        "moisture4": 100.0,
        "nitrogen": 1.32,
        "phosphorus": 4.46,
        "potassium": 4.22,
        "ec": 1336.0,
        "ph": 8.0,
        "timestamp": "2025-02-23T00:39:48+01:00"
    },
    {
        "id": 287,
        "temperature": 17.33,
        "humidity": 80.55,
        "co2": 491.0,
        "light": 0.0,
        "wind_speed": 0.0,
        "moisture1": 100.0,
        "moisture2": 98.77,
        "moisture3": 99.12,
        "moisture4": 100.0,
        "nitrogen": 1.3,
        "phosphorus": 4.47,
        "potassium": 4.22,
        "ec": 1331.0,
        "ph": 7.6,
        "timestamp": "2025-02-23T00:49:48+01:00"
    },
    {
        "id": 288,
        "temperature": 17.33,
        "humidity": 80.44,
        "co2": 491.0,
        "light": 0.0,
        "wind_speed": 0.0,
        "moisture1": 100.0,
        "moisture2": 99.12,
        "moisture3": 100.0,
        "moisture4": 100.0,
        "nitrogen": 1.24,
        "phosphorus": 4.52,
        "potassium": 4.24,
        "ec": 1334.0,
        "ph": 7.8,
        "timestamp": "2025-02-23T00:59:48+01:00"
    }
]