[
    {
        "id": 366,
        "temperature": 16.81,
        "humidity": 81.61,
        "co2": 447.0,
        "light": 7.92,
        "wind_speed": 0.0,
        "moisture1": 100.0,
        "moisture2": 98.71,
        "moisture3": 99.82,
        "moisture4": 100.0,
        "nitrogen": 1.24,
        "phosphorus": 4.48,
        "potassium": 4.27,
        "ec": 1316.0,
        "ph": 7.7,
        "timestamp": "2025-02-23T14:09:47+01:00"
    },
    {
        "id": 367,
        "temperature": 16.84,
        "humidity": 81.26,
        "co2": 442.0,
        "light": 7.5,
        "wind_speed": 0.0,
        "moisture1": 100.0,
        "moisture2": 99.24,
        "moisture3": 100.0,
        "moisture4": 100.0,
        "nitrogen": 1.33,
        "phosphorus": 4.46,
        "potassium": 4.22,
        "ec": 1314.0,
        "ph": 7.5,
        "timestamp": "2025-02-23T14:19:48+01:00"
    }
]