[
    {
        "id": 442,
        "temperature": 20.26,
        "humidity": 75.15,
        "co2": 464.0,
        "light": 27.5,
        "wind_speed": 0.0,
        "moisture1": 31.86,
        "moisture2": 99.12,
        "moisture3": 100.0,
        "moisture4": 36.74,
        "nitrogen": 1.0,
        "phosphorus": 7.76,
        "potassium": 1.24,
        "ec": 1269.0,
        "ph": 7.6,
        "timestamp": "2025-04-11T14:03:08+02:00"
    },
    {
        "id": 443,
        "temperature": 20.31,
        "humidity": 74.66,
        "co2": 454.0,
        "light": 26.67,
        "wind_speed": 0.0,
        "moisture1": 33.74,
        "moisture2": 100.0,
        "moisture3": 100.0,
        "moisture4": 40.86,
        "nitrogen": 0.99,
        "phosphorus": 7.79,
        "potassium": 1.22,
        "ec": 1270.0,
        "ph": 7.6,
        "timestamp": "2025-04-11T14:13:09+02:00"
    },
    {
        "id": 444,
        "temperature": 20.34,
        "humidity": 74.64,
        "co2": 456.0,
        "light": 26.25,
        "wind_speed": 0.0,
        "moisture1": 30.45,
        "moisture2": 98.88,
        "moisture3": 100.0,
        "moisture4": 36.8,
        "nitrogen": 1.01,
        "phosphorus": 7.77,
        "potassium": 1.22,
        "ec": 1275.0,
        "ph": 7.6,
        "timestamp": "2025-04-11T14:23:09+02:00"
    },
    {
        "id": 445,
        "temperature": 20.35,
        "humidity": 74.82,
        "co2": 455.0,
        "light": 25.42,
        "wind_speed": 0.0,
        "moisture1": 30.92,
        "moisture2": 99.35,
        "moisture3": 100.0,
        "moisture4": 37.57,
        "nitrogen": 1.01,
        "phosphorus": 7.77,
        "potassium": 1.22,
        "ec": 1273.0,
        "ph": 7.6,
        "timestamp": "2025-04-11T14:33:08+02:00"
    },
    {
        "id": 446,
        "temperature": 20.41,
        "humidity": 75.15,
        "co2": 471.0,
        "light": 25.0,
        "wind_speed": 0.0,
        "moisture1": 31.1,
        "moisture2": 98.53,
        "moisture3": 100.0,
        "moisture4": 35.21,
        "nitrogen": 1.0,
        "phosphorus": 7.81,
        "potassium": 1.18,
        "ec": 1273.0,
        "ph": 7.6,
        "timestamp": "2025-04-11T14:43:09+02:00"
    }
]