[
    {
        "id": 766,
        "temperature": 21.27,
        "humidity": 75.18,
        "co2": 485.0,
        "light": 60.42,
        "wind_speed": 0.0,
        "moisture1": 20.16,
        "moisture2": 40.68,
        "moisture3": 95.24,
        "moisture4": 100.0,
        "nitrogen": 1.29,
        "phosphorus": 7.62,
        "potassium": 1.08,
        "ec": 996.0,
        "ph": 8.4,
        "timestamp": "2025-04-16T11:06:09+02:00"
    },
    {
        "id": 767,
        "temperature": 21.25,
        "humidity": 75.22,
        "co2": 469.0,
        "light": 54.17,
        "wind_speed": 0.0,
        "moisture1": 20.34,
        "moisture2": 41.39,
        "moisture3": 94.71,
        "moisture4": 100.0,
        "nitrogen": 1.33,
        "phosphorus": 7.5,
        "potassium": 1.17,
        "ec": 996.0,
        "ph": 8.4,
        "timestamp": "2025-04-16T11:16:09+02:00"
    },
    {
        "id": 768,
        "temperature": 21.23,
        "humidity": 75.52,
        "co2": 478.0,
        "light": 58.33,
        "wind_speed": 0.0,
        "moisture1": 21.05,
        "moisture2": 41.33,
        "moisture3": 97.59,
        "moisture4": 100.0,
        "nitrogen": 1.32,
        "phosphorus": 7.55,
        "potassium": 1.13,
        "ec": 998.0,
        "ph": 8.4,
        "timestamp": "2025-04-16T11:26:09+02:00"
    },
    {
        "id": 769,
        "temperature": 21.23,
        "humidity": 75.81,
        "co2": 492.0,
        "light": 46.67,
        "wind_speed": 0.0,
        "moisture1": 20.81,
        "moisture2": 38.04,
        "moisture3": 96.88,
        "moisture4": 100.0,
        "nitrogen": 1.3,
        "phosphorus": 7.57,
        "potassium": 1.13,
        "ec": 995.0,
        "ph": 8.4,
        "timestamp": "2025-04-16T11:36:09+02:00"
    }
]